<root>
    <item name='org.bukkit.permissions.PermissibleBase org.bukkit.permissions.PermissionAttachment addAttachment(org.bukkit.plugin.Plugin, int) 0'>
        <annotation name='org.jetbrains.annotations.NotNull'/>
    </item>
    <item name='org.bukkit.permissions.Permission org.bukkit.permissions.Permission loadPermission(java.lang.String, java.util.Map&lt;?,?&gt;, org.bukkit.permissions.PermissionDefault, java.util.List&lt;org.bukkit.permissions.Permission&gt;) 1'>
        <annotation name='org.jetbrains.annotations.NotNull'/>
    </item>
    <item name='org.bukkit.permissions.Permissible boolean isPermissionSet(org.bukkit.permissions.Permission) 0'>
        <annotation name='org.jetbrains.annotations.NotNull'/>
        <annotation name='org.jetbrains.kannotator.runtime.annotations.Propagated'>
            <val name="value" val="{org.jetbrains.kannotator.controlFlow.builder.analysis.NullabilityKey.class}"/>
        </annotation>
    </item>
    <item name='org.bukkit.permissions.PermissionDefault org.bukkit.permissions.PermissionDefault[] values()'>
        <annotation name='org.jetbrains.annotations.NotNull'/>
    </item>
    <item name='org.bukkit.permissions.PermissionAttachment org.bukkit.plugin.Plugin getPlugin()'>
        <annotation name='org.jetbrains.annotations.NotNull'/>
    </item>
    <item name='org.bukkit.permissions.Permissible org.bukkit.permissions.PermissionAttachment addAttachment(org.bukkit.plugin.Plugin, java.lang.String, boolean) 1'>
        <annotation name='org.jetbrains.annotations.NotNull'/>
        <annotation name='org.jetbrains.kannotator.runtime.annotations.Propagated'>
            <val name="value" val="{org.jetbrains.kannotator.controlFlow.builder.analysis.NullabilityKey.class}"/>
        </annotation>
    </item>
    <item name='org.bukkit.permissions.PermissibleBase org.bukkit.permissions.PermissionAttachment addAttachment(org.bukkit.plugin.Plugin, java.lang.String, boolean) 0'>
        <annotation name='org.jetbrains.annotations.NotNull'/>
    </item>
    <item name='org.bukkit.permissions.Permissible org.bukkit.permissions.PermissionAttachment addAttachment(org.bukkit.plugin.Plugin) 0'>
        <annotation name='org.jetbrains.annotations.NotNull'/>
        <annotation name='org.jetbrains.kannotator.runtime.annotations.Propagated'>
            <val name="value" val="{org.jetbrains.kannotator.controlFlow.builder.analysis.NullabilityKey.class}"/>
        </annotation>
    </item>
    <item name='org.bukkit.permissions.Permission org.bukkit.permissions.Permission loadPermission(java.lang.String, java.util.Map&lt;?,?&gt;, org.bukkit.permissions.PermissionDefault, java.util.List&lt;org.bukkit.permissions.Permission&gt;)'>
        <annotation name='org.jetbrains.annotations.NotNull'/>
    </item>
    <item name='org.bukkit.permissions.PermissibleBase org.bukkit.permissions.PermissionAttachment addAttachment(org.bukkit.plugin.Plugin, java.lang.String, boolean)'>
        <annotation name='org.jetbrains.annotations.NotNull'/>
    </item>
    <item name='org.bukkit.permissions.Permission void addParent(org.bukkit.permissions.Permission, boolean) 0'>
        <annotation name='org.jetbrains.annotations.NotNull'/>
    </item>
    <item name='org.bukkit.permissions.PermissionAttachmentInfo java.lang.String getPermission()'>
        <annotation name='org.jetbrains.annotations.NotNull'/>
    </item>
    <item name='org.bukkit.permissions.Permissible org.bukkit.permissions.PermissionAttachment addAttachment(org.bukkit.plugin.Plugin, java.lang.String, boolean)'>
        <annotation name='org.jetbrains.annotations.NotNull'/>
        <annotation name='org.jetbrains.kannotator.runtime.annotations.Propagated'>
            <val name="value" val="{org.jetbrains.kannotator.controlFlow.builder.analysis.NullabilityKey.class}"/>
        </annotation>
    </item>
    <item name='org.bukkit.permissions.PermissibleBase org.bukkit.permissions.PermissionAttachment addAttachment(org.bukkit.plugin.Plugin, java.lang.String, boolean, int) 1'>
        <annotation name='org.jetbrains.annotations.NotNull'/>
    </item>
    <item name='org.bukkit.permissions.PermissionDefault FALSE'>
        <annotation name='org.jetbrains.annotations.NotNull'/>
    </item>
    <item name='org.bukkit.permissions.PermissionDefault NOT_OP'>
        <annotation name='org.jetbrains.annotations.NotNull'/>
    </item>
    <item name='org.bukkit.permissions.Permissible void removeAttachment(org.bukkit.permissions.PermissionAttachment) 0'>
        <annotation name='org.jetbrains.annotations.NotNull'/>
        <annotation name='org.jetbrains.kannotator.runtime.annotations.Propagated'>
            <val name="value" val="{org.jetbrains.kannotator.controlFlow.builder.analysis.NullabilityKey.class}"/>
        </annotation>
    </item>
    <item name='org.bukkit.permissions.Permissible org.bukkit.permissions.PermissionAttachment addAttachment(org.bukkit.plugin.Plugin, java.lang.String, boolean, int) 1'>
        <annotation name='org.jetbrains.annotations.NotNull'/>
        <annotation name='org.jetbrains.kannotator.runtime.annotations.Propagated'>
            <val name="value" val="{org.jetbrains.kannotator.controlFlow.builder.analysis.NullabilityKey.class}"/>
        </annotation>
    </item>
    <item name='org.bukkit.permissions.Permissible org.bukkit.permissions.PermissionAttachment addAttachment(org.bukkit.plugin.Plugin, java.lang.String, boolean) 0'>
        <annotation name='org.jetbrains.annotations.NotNull'/>
        <annotation name='org.jetbrains.kannotator.runtime.annotations.Propagated'>
            <val name="value" val="{org.jetbrains.kannotator.controlFlow.builder.analysis.NullabilityKey.class}"/>
        </annotation>
    </item>
    <item name='org.bukkit.permissions.Permission DEFAULT_PERMISSION'>
        <annotation name='org.jetbrains.annotations.NotNull'/>
    </item>
    <item name='org.bukkit.permissions.PermissibleBase org.bukkit.permissions.PermissionAttachment addAttachment(org.bukkit.plugin.Plugin) 0'>
        <annotation name='org.jetbrains.annotations.NotNull'/>
    </item>
    <item name='org.bukkit.permissions.Permission org.bukkit.permissions.Permission loadPermission(java.lang.String, java.util.Map&lt;java.lang.String,java.lang.Object&gt;) 1'>
        <annotation name='org.jetbrains.annotations.NotNull'/>
    </item>
    <item name='org.bukkit.permissions.Permission java.util.List&lt;org.bukkit.permissions.Permission&gt; loadPermissions(java.util.Map&lt;?,?&gt;, java.lang.String, org.bukkit.permissions.PermissionDefault) 0'>
        <annotation name='org.jetbrains.annotations.NotNull'/>
    </item>
    <item name='org.bukkit.permissions.Permissible org.bukkit.permissions.PermissionAttachment addAttachment(org.bukkit.plugin.Plugin)'>
        <annotation name='org.jetbrains.annotations.NotNull'/>
        <annotation name='org.jetbrains.kannotator.runtime.annotations.Propagated'>
            <val name="value" val="{org.jetbrains.kannotator.controlFlow.builder.analysis.NullabilityKey.class}"/>
        </annotation>
    </item>
    <item name='org.bukkit.permissions.Permissible java.util.Set&lt;org.bukkit.permissions.PermissionAttachmentInfo&gt; getEffectivePermissions()'>
        <annotation name='org.jetbrains.annotations.NotNull'/>
        <annotation name='org.jetbrains.kannotator.runtime.annotations.Propagated'>
            <val name="value" val="{org.jetbrains.kannotator.controlFlow.builder.analysis.NullabilityKey.class}"/>
        </annotation>
    </item>
    <item name='org.bukkit.permissions.PermissibleBase boolean hasPermission(java.lang.String) 0'>
        <annotation name='org.jetbrains.annotations.NotNull'/>
    </item>
    <item name='org.bukkit.permissions.PermissibleBase org.bukkit.permissions.PermissionAttachment addAttachment(org.bukkit.plugin.Plugin, java.lang.String, boolean, int) 0'>
        <annotation name='org.jetbrains.annotations.NotNull'/>
    </item>
    <item name='org.bukkit.permissions.PermissionDefault TRUE'>
        <annotation name='org.jetbrains.annotations.NotNull'/>
    </item>
    <item name='org.bukkit.permissions.PermissionAttachment void unsetPermission(org.bukkit.permissions.Permission) 0'>
        <annotation name='org.jetbrains.annotations.NotNull'/>
    </item>
    <item name='org.bukkit.permissions.Permission java.util.Map&lt;java.lang.String,java.lang.Boolean&gt; getChildren()'>
        <annotation name='org.jetbrains.annotations.NotNull'/>
    </item>
    <item name='org.bukkit.permissions.Permission java.util.List&lt;org.bukkit.permissions.Permission&gt; loadPermissions(java.util.Map&lt;?,?&gt;, java.lang.String, org.bukkit.permissions.PermissionDefault)'>
        <annotation name='org.jetbrains.annotations.NotNull'/>
    </item>
    <item name='org.bukkit.permissions.PermissibleBase void removeAttachment(org.bukkit.permissions.PermissionAttachment) 0'>
        <annotation name='org.jetbrains.annotations.NotNull'/>
    </item>
    <item name='org.bukkit.permissions.PermissionAttachmentInfo PermissionAttachmentInfo(org.bukkit.permissions.Permissible, java.lang.String, org.bukkit.permissions.PermissionAttachment, boolean) 1'>
        <annotation name='org.jetbrains.annotations.NotNull'/>
    </item>
    <item name='org.bukkit.permissions.Permissible org.bukkit.permissions.PermissionAttachment addAttachment(org.bukkit.plugin.Plugin, java.lang.String, boolean, int) 0'>
        <annotation name='org.jetbrains.annotations.NotNull'/>
        <annotation name='org.jetbrains.kannotator.runtime.annotations.Propagated'>
            <val name="value" val="{org.jetbrains.kannotator.controlFlow.builder.analysis.NullabilityKey.class}"/>
        </annotation>
    </item>
    <item name='org.bukkit.permissions.PermissibleBase boolean hasPermission(org.bukkit.permissions.Permission) 0'>
        <annotation name='org.jetbrains.annotations.NotNull'/>
    </item>
    <item name='org.bukkit.permissions.PermissibleBase boolean isPermissionSet(java.lang.String) 0'>
        <annotation name='org.jetbrains.annotations.NotNull'/>
    </item>
    <item name='org.bukkit.permissions.Permissible boolean isPermissionSet(java.lang.String) 0'>
        <annotation name='org.jetbrains.annotations.NotNull'/>
        <annotation name='org.jetbrains.kannotator.runtime.annotations.Propagated'>
            <val name="value" val="{org.jetbrains.kannotator.controlFlow.builder.analysis.NullabilityKey.class}"/>
        </annotation>
    </item>
    <item name='org.bukkit.permissions.Permission org.bukkit.permissions.Permission loadPermission(java.lang.String, java.util.Map&lt;java.lang.String,java.lang.Object&gt;)'>
        <annotation name='org.jetbrains.annotations.NotNull'/>
    </item>
    <item name='org.bukkit.permissions.Permission org.bukkit.permissions.Permission addParent(java.lang.String, boolean)'>
        <annotation name='org.jetbrains.annotations.NotNull'/>
    </item>
    <item name='org.bukkit.permissions.PermissionAttachment void setPermission(java.lang.String, boolean) 0'>
        <annotation name='org.jetbrains.annotations.NotNull'/>
    </item>
    <item name='org.bukkit.permissions.PermissionAttachmentInfo org.bukkit.permissions.Permissible getPermissible()'>
        <annotation name='org.jetbrains.annotations.NotNull'/>
    </item>
    <item name='org.bukkit.permissions.Permissible org.bukkit.permissions.PermissionAttachment addAttachment(org.bukkit.plugin.Plugin, int) 0'>
        <annotation name='org.jetbrains.annotations.NotNull'/>
        <annotation name='org.jetbrains.kannotator.runtime.annotations.Propagated'>
            <val name="value" val="{org.jetbrains.kannotator.controlFlow.builder.analysis.NullabilityKey.class}"/>
        </annotation>
    </item>
    <item name='org.bukkit.permissions.PermissibleBase boolean isPermissionSet(org.bukkit.permissions.Permission) 0'>
        <annotation name='org.jetbrains.annotations.NotNull'/>
    </item>
    <item name='org.bukkit.permissions.Permissible boolean hasPermission(org.bukkit.permissions.Permission) 0'>
        <annotation name='org.jetbrains.annotations.NotNull'/>
        <annotation name='org.jetbrains.kannotator.runtime.annotations.Propagated'>
            <val name="value" val="{org.jetbrains.kannotator.controlFlow.builder.analysis.NullabilityKey.class}"/>
        </annotation>
    </item>
    <item name='org.bukkit.permissions.PermissionAttachment PermissionAttachment(org.bukkit.plugin.Plugin, org.bukkit.permissions.Permissible) 0'>
        <annotation name='org.jetbrains.annotations.NotNull'/>
    </item>
    <item name='org.bukkit.permissions.PermissionAttachmentInfo PermissionAttachmentInfo(org.bukkit.permissions.Permissible, java.lang.String, org.bukkit.permissions.PermissionAttachment, boolean) 0'>
        <annotation name='org.jetbrains.annotations.NotNull'/>
    </item>
    <item name='org.bukkit.permissions.PermissibleBase org.bukkit.permissions.PermissionAttachment addAttachment(org.bukkit.plugin.Plugin, java.lang.String, boolean) 1'>
        <annotation name='org.jetbrains.annotations.NotNull'/>
    </item>
    <item name='org.bukkit.permissions.PermissibleBase java.util.Set&lt;org.bukkit.permissions.PermissionAttachmentInfo&gt; getEffectivePermissions()'>
        <annotation name='org.jetbrains.annotations.NotNull'/>
    </item>
    <item name='org.bukkit.permissions.Permission org.bukkit.permissions.Permission addParent(java.lang.String, boolean) 0'>
        <annotation name='org.jetbrains.annotations.NotNull'/>
    </item>
    <item name='org.bukkit.permissions.PermissionAttachment java.util.Map&lt;java.lang.String,java.lang.Boolean&gt; getPermissions()'>
        <annotation name='org.jetbrains.annotations.NotNull'/>
    </item>
    <item name='org.bukkit.permissions.PermissionAttachment void setPermission(org.bukkit.permissions.Permission, boolean) 0'>
        <annotation name='org.jetbrains.annotations.NotNull'/>
    </item>
    <item name='org.bukkit.permissions.PermissibleBase org.bukkit.permissions.PermissionAttachment addAttachment(org.bukkit.plugin.Plugin)'>
        <annotation name='org.jetbrains.annotations.NotNull'/>
    </item>
    <item name='org.bukkit.permissions.Permissible boolean hasPermission(java.lang.String) 0'>
        <annotation name='org.jetbrains.annotations.NotNull'/>
        <annotation name='org.jetbrains.kannotator.runtime.annotations.Propagated'>
            <val name="value" val="{org.jetbrains.kannotator.controlFlow.builder.analysis.NullabilityKey.class}"/>
        </annotation>
    </item>
    <item name='org.bukkit.permissions.PermissionDefault OP'>
        <annotation name='org.jetbrains.annotations.NotNull'/>
    </item>
    <item name='org.bukkit.permissions.PermissionAttachment void unsetPermission(java.lang.String) 0'>
        <annotation name='org.jetbrains.annotations.NotNull'/>
    </item>
    <item name='org.bukkit.permissions.PermissionDefault org.bukkit.permissions.PermissionDefault getByName(java.lang.String) 0'>
        <annotation name='org.jetbrains.annotations.NotNull'/>
    </item>
</root>
